clustergram/__init__.py
clustergram/clustergram.py
clustergram/test_clustergram.py
clustergram-0.8.1.dist-info/LICENSE
clustergram-0.8.1.dist-info/METADATA
clustergram-0.8.1.dist-info/WHEEL
clustergram-0.8.1.dist-info/top_level.txt
clustergram-0.8.1.dist-info/RECORD
