Metadata-Version: 2.1
Name: clustergram
Version: 0.8.1
Summary: Clustergram - visualization and diagnostics for cluster analysis
Author-email: Martin Fleischmann <martin@martinfleischmann.net>
Maintainer: Martin Fleischmann
License: MIT
Project-URL: Home, https://clustergram.readthedocs.io
Project-URL: Repository, https://github.com/martinfleis/clustergram
Classifier: Intended Audience :: Science/Research
Classifier: License :: OSI Approved :: MIT License
Classifier: Operating System :: OS Independent
Classifier: Programming Language :: Python :: 3
Requires-Python: >=3.8
License-File: LICENSE
Requires-Dist: pandas
Requires-Dist: numpy
Requires-Dist: matplotlib
